telemetry_peak_analyzer/__init__.py
telemetry_peak_analyzer/__main__.py
telemetry_peak_analyzer/analyzers/__init__.py
telemetry_peak_analyzer/backends/__init__.py
telemetry_peak_analyzer/backends/tina.py
telemetry_peak_analyzer/models/__init__.py
telemetry_peak_analyzer-0.1.6.dist-info/LICENSE
telemetry_peak_analyzer-0.1.6.dist-info/METADATA
telemetry_peak_analyzer-0.1.6.dist-info/NOTICE
telemetry_peak_analyzer-0.1.6.dist-info/WHEEL
telemetry_peak_analyzer-0.1.6.dist-info/entry_points.txt
telemetry_peak_analyzer-0.1.6.dist-info/top_level.txt
telemetry_peak_analyzer-0.1.6.dist-info/RECORD
