Metadata-Version: 2.1
Name: telemetry-peak-analyzer
Version: 0.1.6
Summary: Analyzer to detect peaks when analyzing multi-attribute telemetry feeds
Home-page: https://github.com/vmware-labs/telemetry-peak-analyzer
Author: Stefano Ortolani, Jason Zhang
Project-URL: Bug Tracker, https://github.com/vmware-labs/telemetry-peak-analyzer/issues
Classifier: Development Status :: 3 - Alpha
Classifier: Intended Audience :: Developers
Classifier: License :: OSI Approved :: BSD License
Classifier: Programming Language :: Python :: 3
Classifier: Operating System :: OS Independent
Classifier: Topic :: Security
Classifier: Topic :: System :: Monitoring
Requires-Python: >=3.6
License-File: LICENSE
License-File: NOTICE
Requires-Dist: ijson
Provides-Extra: tina
Requires-Dist: tina-client (>=0.2.1) ; extra == 'tina'
